brbillcode/__init__.py
brbillcode/core/line.py
brbillcode/models/__init__.py
brbillcode/models/bank.py
brbillcode/models/collection.py
brbillcode/utils/__init__.py
brbillcode/utils/modules.py
brbillcode-0.1.1.dist-info/METADATA
brbillcode-0.1.1.dist-info/WHEEL
brbillcode-0.1.1.dist-info/RECORD
