Metadata-Version: 2.3
Name: brbillcode
Version: 0.1.1
Summary: 
Author: Ricardo Castro
Requires-Python: >=3.11
Classifier: Programming Language :: Python :: 3
Classifier: Programming Language :: Python :: 3.11
Classifier: Programming Language :: Python :: 3.12
Classifier: Programming Language :: Python :: 3.13
